ode_filters/__init__.py
ode_filters/filters/__init__.py
ode_filters/filters/ode_filter_loop.py
ode_filters/filters/ode_filter_step.py
ode_filters/inference/__init__.py
ode_filters/inference/sqr_gaussian_inference.py
ode_filters/measurement/__init__.py
ode_filters/measurement/measurement_models.py
ode_filters/priors/__init__.py
ode_filters/priors/gmp_priors.py
ode_filters-0.4.2.dist-info/METADATA
ode_filters-0.4.2.dist-info/WHEEL
ode_filters-0.4.2.dist-info/licenses/LICENSE
ode_filters-0.4.2.dist-info/RECORD
