Metadata-Version: 2.4
Name: ode-filters
Version: 0.4.2
Summary: Basic ODE filtering and smooting implementation.
Author: Paul Fischer
License-Expression: MIT
License-File: LICENSE
Classifier: License :: OSI Approved :: MIT License
Classifier: Operating System :: OS Independent
Classifier: Programming Language :: Python :: 3.13
Classifier: Programming Language :: Python :: 3.14
Requires-Python: >=3.13
Requires-Dist: autograd>=1.8.0
Requires-Dist: jax[cpu]>=0.8.0
Requires-Dist: matplotlib>=3.10.7
Requires-Dist: numpy>=2.3.4
Requires-Dist: pyproject-toml>=0.1.0
Requires-Dist: scikit-learn>=1.7.2
Requires-Dist: tqdm>=4.67.1
Requires-Dist: tueplots>=0.2.1
